pre_commit_odoo/main.py
pre_commit_odoo-0.1.1.dist-info/LICENSE
pre_commit_odoo-0.1.1.dist-info/METADATA
pre_commit_odoo-0.1.1.dist-info/WHEEL
pre_commit_odoo-0.1.1.dist-info/RECORD
