Metadata-Version: 2.1
Name: pre-commit-odoo
Version: 0.1.1
Summary: Checks Odoo modules and projects
Home-page: https://github.com/odoo-ru/pre-commit-odoo
License: MIT
Author: Dmitry Voronin
Author-email: dimka665@gmail.com
Requires-Python: >=3.10,<4.0
Classifier: License :: OSI Approved :: MIT License
Classifier: Programming Language :: Python :: 3
Classifier: Programming Language :: Python :: 3.10
Classifier: Programming Language :: Python :: 3.11
Project-URL: Repository, https://github.com/odoo-ru/pre-commit-odoo
